_hfb3.cpython-311-x86_64-linux-gnu.so
hfb3.py
hfb3/examples/16O_deformed.hfb3
hfb3/examples/16O_deformed.py
hfb3/examples/16O_groundstate.hfb3
hfb3/examples/240Pu_deformed.hfb3
hfb3/examples/240Pu_groundstate.hfb3
hfb3/examples/240Pu_groundstate_WB.hfb3
hfb3/examples/42Ca_deformed_1x11.hfb3
hfb3/examples/42Ca_deformed_1x11.msg.gz
hfb3/examples/42Ca_deformed_2x9.hfb3
hfb3/examples/42Ca_deformed_2x9.msg.gz
hfb3/examples/90Zr_deformed_2x9.hfb3
hfb3/examples/91Zr_deformed_2x9.hfb3
hfb3/examples/demo.ipynb
hfb3/examples/hfb3.png
hfb3.libs/libarmadillo-b35ffa1e.so.12.6.6
hfb3.libs/libarpack-042921fd.so.2.1.0
hfb3.libs/libblas-fe34f726.so.3.8.0
hfb3.libs/libgfortran-83c28eba.so.5.0.0
hfb3.libs/libgomp-e985bcbb.so.1.0.0
hfb3.libs/liblapack-31d7d384.so.3.8.0
hfb3.libs/libopenblaso-r0-d77a1985.3.15.so
hfb3.libs/libopenblasp-r0-59ffcd50.3.15.so
hfb3.libs/libquadmath-2284e583.so.0.0.0
hfb3.libs/libsatlas-6c1f674f.so.3.10
hfb3.libs/libsuperlu-17b63ae5.so.5.1
hfb3-1.0.18.dist-info/METADATA
hfb3-1.0.18.dist-info/WHEEL
hfb3-1.0.18.dist-info/entry_points.txt
hfb3-1.0.18.dist-info/top_level.txt
hfb3-1.0.18.dist-info/RECORD
hfb3-1.0.18.dist-info/licenses/LICENSE
