Metadata-Version: 2.4
Name: hfb3
Version: 1.0.18
Summary: Axial HFB solver with Gogny forces using a 2-center HO basis
Author-email: "Dubray N." <noel.dubray@cea.fr>
Maintainer-email: "Dubray N." <noel.dubray@cea.fr>
License: GPL-3.0-or-later
Project-URL: Homepage, https://github.com/cea-phynu/hfb3
Project-URL: Bug Tracker, https://github.com/cea-phynu/hfb3/issues
Classifier: Programming Language :: Python :: 3
Classifier: Operating System :: OS Independent
Classifier: Topic :: Scientific/Engineering :: Physics
Requires-Python: >=3.8
License-File: LICENSE
Requires-Dist: numpy
Dynamic: license-file
